hard_connect/__init__.py
hard_connect/base_modbus.py
hard_connect/base_serial.py
hard_connect/base_socket.py
hard_connect/hard_conn.py
hard_connect/log.py
hard_connect/utils.py
hard_connect-0.3.2.dist-info/METADATA
hard_connect-0.3.2.dist-info/WHEEL
hard_connect-0.3.2.dist-info/top_level.txt
hard_connect-0.3.2.dist-info/RECORD
