Metadata-Version: 2.1
Name: hard-connect
Version: 0.3.2
Summary: Connect hard device, socket or serial
Author: kingduyin
Author-email: kingduyin@gmail.com
Requires-Python: >=3.6
Requires-Dist: pyserial ==3.5
Requires-Dist: pymodbus ==3.6.8
